diyepw/__init__.py
diyepw/_logging.py
diyepw/analyze_noaa_isd_lite_file.py
diyepw/analyze_noaa_isd_lite_files.py
diyepw/create_amy_epw_file.py
diyepw/create_amy_epw_files_for_years_and_wmos.py
diyepw/exceptions.py
diyepw/get_noaa_isd_lite_file.py
diyepw/get_tmy_epw_file.py
diyepw/get_wmo_station_location.py
diyepw/meteorology.py
diyepw/data/Weather_Stations_by_County.csv
diyepw/data/noaa_isd_lite_catalogs/1990
diyepw/data/noaa_isd_lite_catalogs/1991
diyepw/data/noaa_isd_lite_catalogs/1992
diyepw/data/noaa_isd_lite_catalogs/1993
diyepw/data/noaa_isd_lite_catalogs/1994
diyepw/data/noaa_isd_lite_catalogs/1995
diyepw/data/noaa_isd_lite_catalogs/1996
diyepw/data/noaa_isd_lite_catalogs/1997
diyepw/data/noaa_isd_lite_catalogs/1998
diyepw/data/noaa_isd_lite_catalogs/1999
diyepw/data/noaa_isd_lite_catalogs/2000
diyepw/data/noaa_isd_lite_catalogs/2001
diyepw/data/noaa_isd_lite_catalogs/2002
diyepw/data/noaa_isd_lite_catalogs/2003
diyepw/data/noaa_isd_lite_catalogs/2004
diyepw/data/noaa_isd_lite_catalogs/2005
diyepw/data/noaa_isd_lite_catalogs/2006
diyepw/data/noaa_isd_lite_catalogs/2007
diyepw/data/noaa_isd_lite_catalogs/2008
diyepw/data/noaa_isd_lite_catalogs/2009
diyepw/data/noaa_isd_lite_catalogs/2010
diyepw/data/noaa_isd_lite_catalogs/2011
diyepw/data/noaa_isd_lite_catalogs/2012
diyepw/data/noaa_isd_lite_catalogs/2013
diyepw/data/noaa_isd_lite_catalogs/2014
diyepw/data/noaa_isd_lite_catalogs/2015
diyepw/data/noaa_isd_lite_catalogs/2016
diyepw/data/noaa_isd_lite_catalogs/2017
diyepw/data/noaa_isd_lite_catalogs/2018
diyepw/data/noaa_isd_lite_catalogs/2019
diyepw/data/noaa_isd_lite_catalogs/2020
diyepw/data/noaa_isd_lite_catalogs/2021
diyepw/data/noaa_isd_lite_catalogs/README.md
diyepw/data/noaa_isd_lite_files/702910-2018.gz
diyepw/data/noaa_isd_lite_files/702910-2019.gz
diyepw/data/noaa_isd_lite_files/725300-2015.gz
diyepw/data/noaa_isd_lite_files/725300-2016.gz
diyepw/data/noaa_isd_lite_files/725300-2017.gz
diyepw/data/noaa_isd_lite_files/725957-2015.gz
diyepw-1.3.1.dist-info/licenses/LICENSE
diyepw-1.3.1.dist-info/METADATA
diyepw-1.3.1.dist-info/WHEEL
diyepw-1.3.1.dist-info/entry_points.txt
diyepw-1.3.1.dist-info/top_level.txt
diyepw-1.3.1.dist-info/RECORD
