Metadata-Version: 2.4
Name: diyepw
Version: 1.3.1
Summary: A package offering support for generating EPW (EnergyPlus Weather) files
Home-page: https://github.com/IMMM-SFA/diyepw
Author: Amanda Smith
Author-email: amanda.d.smith@pnnl.gov
License: BSD 2-Clause
Requires-Python: >=3.9
License-File: LICENSE
Requires-Dist: click<9.0.0,>=8.0.1
Requires-Dist: numpy<3.0.0,>=2.0.0
Requires-Dist: pandas<3.0.0,>=2.2.0
Requires-Dist: pvlib<1.0.0,>=0.13.0
Requires-Dist: xarray<2026.0.0,>=2024.0.0
Requires-Dist: importlib_resources<7.0.0,>=6.0.0
Provides-Extra: dev
Requires-Dist: build>=0.5.1; extra == "dev"
Requires-Dist: pytest>=6.2.4; extra == "dev"
Requires-Dist: twine>=3.4.1; extra == "dev"
Requires-Dist: recommonmark~=0.7.1; extra == "dev"
Requires-Dist: setuptools>=58.0.0; extra == "dev"
Requires-Dist: sphinx~=3.5.1; extra == "dev"
Requires-Dist: sphinx-rtd-theme~=0.5.1; extra == "dev"
Dynamic: author
Dynamic: author-email
Dynamic: description
Dynamic: description-content-type
Dynamic: home-page
Dynamic: license
Dynamic: license-file
Dynamic: provides-extra
Dynamic: requires-dist
Dynamic: requires-python
Dynamic: summary
